{
  "@context": "http://iiif.io/api/image/3/context.json",
  "id": "https://hackathan-iiif.onrender.com/br_rjanrio_o2_0_fot_0046/1beb171ba83c7e43a6c344eee115913a",
  "type": "ImageService3",
  "profile": "level0",
  "protocol": "http://iiif.io/api/image",
  "tiles": [
    {
      "scaleFactors": [
        1,
        2
      ],
      "width": 256
    }
  ],
  "width": 704,
  "height": 1024,
  "sizes": [
    {
      "width": 206,
      "height": 300
    },
    {
      "width": 704,
      "height": 1024
    }
  ]
}